tom_iag/__init__.py
tom_iag/iag.py
tom_iag-0.2.13.dist-info/LICENSE
tom_iag-0.2.13.dist-info/METADATA
tom_iag-0.2.13.dist-info/WHEEL
tom_iag-0.2.13.dist-info/RECORD
