Metadata-Version: 2.3
Name: tom-iag
Version: 0.2.13
Summary: IAG telescopes facility module for the TOM Toolkit
Home-page: https://github.com/thusser/tom_iag
License: MIT
Author: Tim-Oliver Husser
Author-email: thusser@uni-goettingen.de
Requires-Python: >=3.7,<3.13
Classifier: License :: OSI Approved :: MIT License
Classifier: Programming Language :: Python :: 3
Classifier: Programming Language :: Python :: 3.7
Classifier: Programming Language :: Python :: 3.8
Classifier: Programming Language :: Python :: 3.9
Classifier: Programming Language :: Python :: 3.10
Classifier: Programming Language :: Python :: 3.11
Classifier: Programming Language :: Python :: 3.12
Project-URL: Repository, https://github.com/thusser/tom_iag
